tna_frontend_jinja/__init__.py
tna_frontend_jinja/templates/components/accordion/macro.html
tna_frontend_jinja/templates/components/back-link/macro.html
tna_frontend_jinja/templates/components/breadcrumbs/macro.html
tna_frontend_jinja/templates/components/button/macro.html
tna_frontend_jinja/templates/components/card/macro.html
tna_frontend_jinja/templates/components/checkboxes/macro.html
tna_frontend_jinja/templates/components/compound-filters/macro.html
tna_frontend_jinja/templates/components/cookie-banner/macro.html
tna_frontend_jinja/templates/components/date-input/macro.html
tna_frontend_jinja/templates/components/date-search/macro.html
tna_frontend_jinja/templates/components/details/macro.html
tna_frontend_jinja/templates/components/error-summary/macro.html
tna_frontend_jinja/templates/components/fieldset/macro.html
tna_frontend_jinja/templates/components/file-input/macro.html
tna_frontend_jinja/templates/components/files-list/macro.html
tna_frontend_jinja/templates/components/footer/macro.html
tna_frontend_jinja/templates/components/gallery/macro.html
tna_frontend_jinja/templates/components/global-header/macro.html
tna_frontend_jinja/templates/components/header/macro.html
tna_frontend_jinja/templates/components/hero/macro.html
tna_frontend_jinja/templates/components/index-grid/macro.html
tna_frontend_jinja/templates/components/pagination/macro.html
tna_frontend_jinja/templates/components/panel/macro.html
tna_frontend_jinja/templates/components/phase-banner/macro.html
tna_frontend_jinja/templates/components/picture/macro.html
tna_frontend_jinja/templates/components/quick-filters/macro.html
tna_frontend_jinja/templates/components/radios/macro.html
tna_frontend_jinja/templates/components/search-field/macro.html
tna_frontend_jinja/templates/components/secondary-navigation/macro.html
tna_frontend_jinja/templates/components/select/macro.html
tna_frontend_jinja/templates/components/sidebar/macro.html
tna_frontend_jinja/templates/components/skip-link/macro.html
tna_frontend_jinja-0.32.0.dist-info/licenses/LICENCE
tna_frontend_jinja-0.32.0.dist-info/METADATA
tna_frontend_jinja-0.32.0.dist-info/WHEEL
tna_frontend_jinja-0.32.0.dist-info/top_level.txt
tna_frontend_jinja-0.32.0.dist-info/RECORD
