Metadata-Version: 2.4
Name: tna-frontend-jinja
Version: 0.32.0
Summary: TNA Frontend Jinja templates
Home-page: https://github.com/nationalarchives/tna-frontend-jinja
Author: Andrew Hosgood
Author-email: andrew.hosgood@nationalarchives.gov.uk
Project-URL: Bug Tracker, https://github.com/nationalarchives/tna-frontend-jinja/issues
Classifier: Programming Language :: Python :: 3
Classifier: License :: OSI Approved :: MIT License
Classifier: Operating System :: OS Independent
Classifier: Environment :: Web Environment
Classifier: Intended Audience :: Developers
Classifier: Topic :: Software Development :: Code Generators
Classifier: Topic :: Software Development :: User Interfaces
Classifier: Topic :: Text Processing :: Markup :: HTML
Requires-Python: >=3.9
License-File: LICENCE
Requires-Dist: Jinja2>=3
Dynamic: author
Dynamic: author-email
Dynamic: classifier
Dynamic: description
Dynamic: description-content-type
Dynamic: home-page
Dynamic: license-file
Dynamic: project-url
Dynamic: requires-dist
Dynamic: requires-python
Dynamic: summary
